CHANGES.txt
CONTRIBUTORS.txt
MANIFEST.in
README.rst
TODOS.rst
setup.py
src/eea/__init__.py
src/eea.facetednavigationtaxonomiccheckbox.egg-info/PKG-INFO
src/eea.facetednavigationtaxonomiccheckbox.egg-info/SOURCES.txt
src/eea.facetednavigationtaxonomiccheckbox.egg-info/dependency_links.txt
src/eea.facetednavigationtaxonomiccheckbox.egg-info/entry_points.txt
src/eea.facetednavigationtaxonomiccheckbox.egg-info/namespace_packages.txt
src/eea.facetednavigationtaxonomiccheckbox.egg-info/not-zip-safe
src/eea.facetednavigationtaxonomiccheckbox.egg-info/requires.txt
src/eea.facetednavigationtaxonomiccheckbox.egg-info/top_level.txt
src/eea/facetednavigationtaxonomiccheckbox/__init__.py
src/eea/facetednavigationtaxonomiccheckbox/configure.zcml
src/eea/facetednavigationtaxonomiccheckbox/edit.css
src/eea/facetednavigationtaxonomiccheckbox/edit.js
src/eea/facetednavigationtaxonomiccheckbox/testing.py
src/eea/facetednavigationtaxonomiccheckbox/view.css
src/eea/facetednavigationtaxonomiccheckbox/view.js
src/eea/facetednavigationtaxonomiccheckbox/widget.pt
src/eea/facetednavigationtaxonomiccheckbox/widget.py
src/eea/facetednavigationtaxonomiccheckbox/profiles/default/metadata.xml
src/eea/facetednavigationtaxonomiccheckbox/tests/__init__.py
src/eea/facetednavigationtaxonomiccheckbox/tests/base.py
src/eea/facetednavigationtaxonomiccheckbox/tests/test_generic.py