Metadata-Version: 1.0
Name: eea.facetednavigationtaxonomiccheckbox
Version: 0.1
Summary: Taxonomic tags in EEA Faceted Navigation.
Home-page: https://github.com/collective/eea.facetednavigationtaxonomiccheckbox
Author: Goldmund, Wyldebeast & Wunderliebe
Author-email: info@gw20e.com
License: GPL 2.0
Keywords: taxonomic tags,nested tags,eea.facetednavigation
Platform: UNKNOWN
Classifier: Environment :: Web Environment
Classifier: Framework :: Plone
Classifier: Operating System :: OS Independent
Classifier: Programming Language :: Python
Classifier: Programming Language :: Python :: 2.6
Classifier: Topic :: Software Development :: Libraries :: Python Modules
